{"name":"Xabier","age":39,"office":""}
{"name":"Miguel","office":"RIO"}
{"name":"Fran","age":31,"office":"RIO"}
{"name":"Ana","age":25,"office":"MAD"}
{"name":"Lucia","age":29,"office":"MAD"}
{"name":"Laura","age":27,"office":"MAD"}
{"name":"Alvaro","age":35,"office":"MAD"}
{"name":"Sergio","age":30,"office":"MAD"}
{"name":"Pablo","age":28,"office":"MAD"}
{"name":"Diego","age":32,"office":"MAD"}
{"name":"Marta","age":26,"office":"MAD"}
{"name":"Carmen","age":24,"office":"MAD"}
{"name":"Jose","age":40,"office":"MAD"}
{"name":"Luis","age":38,"office":"MAD"}
{"name":"Elena","age":33,"office":"MAD"}
{"name":"Isabel","age":34,"office":"MAD"}
{"name":"Javier","age":36,"office":"MAD"}
{"name":"Raul","age":37,"office":"MAD"}
{"name":"Sofia","age":23,"office":"MAD"}
{"name":"Clara","age":22,"office":"MAD"}
{"name":"Nuria","age":21,"office":"MAD"}
{"name":"Alba","age":20,"office":"MAD"}